<?xml version="1.0"?>
<ArrayOfProduct xmlns:xsi="http://www.w3.org/2001/XMLSchema-instance" xmlns:xsd="http://www.w3.org/2001/XMLSchema">
  <Product>
    <ProductId>7055fc76-5afd-4a24-aa1d-5cab092b797a</ProductId>
    <Name>nulla</Name>
    <Price>1111111111111</Price>
  </Product>
  <Product>
    <ProductId>c3b20f7a-c6e3-4382-86a7-fc2d4a993cff</ProductId>
    <Name>eiusmod</Name>
    <Price>-84193200.46060447</Price>
  </Product>
  <Product>
    <ProductId>20c7a246-68d3-48d0-9041-d2a7c40e0d9a</ProductId>
    <Name>laboris eu</Name>
    <Price>22222222</Price>
  </Product>
  <Product>
    <ProductId>2b3294c2-86a3-4958-ad7b-5a33ae8d8b55</ProductId>
    <Name>non eu eiusmod</Name>
    <Price>3333333333</Price>
  </Product>
  <Product>
    <ProductId>73195ddb-a085-433e-af07-e240156fe1a1</ProductId>
    <Name>nulla</Name>
    <Price>1111111111111</Price>
  </Product>
  <Product>
    <ProductId>cfa6efd8-ab10-4800-b2a7-3de15f296ce2</ProductId>
    <Name>eiusmod</Name>
    <Price>-84193200.46060447</Price>
  </Product>
  <Product>
    <ProductId>ee0d309e-3385-49dd-8f7b-a690b7f241f9</ProductId>
    <Name>laboris eu</Name>
    <Price>22222222</Price>
  </Product>
  <Product>
    <ProductId>b7b872bb-61ed-4428-be4d-e96b374412c1</ProductId>
    <Name>non eu eiusmod</Name>
    <Price>3333333333</Price>
  </Product>
  <Product>
    <ProductId>a8d0fb3a-3b74-4d66-a215-d6be044ae666</ProductId>
    <Name>nulla</Name>
    <Price>1111111111111</Price>
  </Product>
  <Product>
    <ProductId>9fee0623-bc46-4397-bc9c-0bdb55773cf5</ProductId>
    <Name>eiusmod</Name>
    <Price>-84193200.46060447</Price>
  </Product>
  <Product>
    <ProductId>a66058a9-766b-49cd-affb-22bd5a419b9d</ProductId>
    <Name>laboris eu</Name>
    <Price>22222222</Price>
  </Product>
  <Product>
    <ProductId>f1601201-0e73-48eb-a80d-c4cafc47fd21</ProductId>
    <Name>non eu eiusmod</Name>
    <Price>3333333333</Price>
  </Product>
  <Product>
    <ProductId>627f7f4f-10bb-4a84-b009-a669eac44fbc</ProductId>
    <Name>nulla</Name>
    <Price>1111111111111</Price>
  </Product>
  <Product>
    <ProductId>2afb20b0-9f85-4297-865a-661647daeba4</ProductId>
    <Name>eiusmod</Name>
    <Price>-84193200.46060447</Price>
  </Product>
  <Product>
    <ProductId>2407ca11-561e-4634-8c76-cd645d141642</ProductId>
    <Name>laboris eu</Name>
    <Price>22222222</Price>
  </Product>
  <Product>
    <ProductId>2ee09acc-5844-4d24-bbbf-d76ad16da593</ProductId>
    <Name>non eu eiusmod</Name>
    <Price>3333333333</Price>
  </Product>
  <Product>
    <ProductId>f58a3ad3-7f09-4748-aae8-95ad3ea34f94</ProductId>
    <Name>nulla</Name>
    <Price>1111111111111</Price>
  </Product>
  <Product>
    <ProductId>10e27460-1c3a-4ff2-b364-42209abd4ebe</ProductId>
    <Name>eiusmod</Name>
    <Price>-84193200.46060447</Price>
  </Product>
  <Product>
    <ProductId>3e60567f-9186-41da-9ab4-8822f3eafac1</ProductId>
    <Name>laboris eu</Name>
    <Price>22222222</Price>
  </Product>
  <Product>
    <ProductId>6700752e-bdcf-4278-974c-d6b06ca02eae</ProductId>
    <Name>non eu eiusmod</Name>
    <Price>3333333333</Price>
  </Product>
  <Product>
    <ProductId>09dbd2da-077f-42a8-ad29-83a828f80ccb</ProductId>
    <Name>nulla</Name>
    <Price>111</Price>
  </Product>
  <Product>
    <ProductId>3173a958-9a49-4cf1-b2df-8452ea1ce995</ProductId>
    <Name>eiusmod</Name>
    <Price>222</Price>
  </Product>
  <Product>
    <ProductId>b34248b1-0208-4641-b141-16ffb9b3c579</ProductId>
    <Name>nulla</Name>
    <Price>111</Price>
  </Product>
  <Product>
    <ProductId>5b1a4981-af88-4c28-bb80-0c29cce557b7</ProductId>
    <Name>eiusmod</Name>
    <Price>222</Price>
  </Product>
</ArrayOfProduct>